.gitignore
.pyflymakerc
.travis.yml
GPL-V3.0.txt
MANIFEST.in
README.html
README.rst
README.txt
requirements.txt
setenv.sh
setup.cfg
setup.py
setup_data.py
CodeReview/Version.py
CodeReview/__init__.py
CodeReview.egg-info/PKG-INFO
CodeReview.egg-info/SOURCES.txt
CodeReview.egg-info/dependency_links.txt
CodeReview.egg-info/entry_points.txt
CodeReview.egg-info/not-zip-safe
CodeReview.egg-info/requires.txt
CodeReview.egg-info/top_level.txt
CodeReview/Application/ApplicationBase.py
CodeReview/Application/__init__.py
CodeReview/Common/ArgparseAction.py
CodeReview/Common/AttributeDictionaryInterface.py
CodeReview/Common/BackTrace.py
CodeReview/Common/EnumFactory.py
CodeReview/Common/IteratorTools.py
CodeReview/Common/Path.py
CodeReview/Common/Platform.py
CodeReview/Common/Platform2.py
CodeReview/Common/ProgramOptions.py
CodeReview/Common/RevisionVersion.py
CodeReview/Common/Singleton.py
CodeReview/Common/Slice.py
CodeReview/Common/StringTools.py
CodeReview/Common/__init__.py
CodeReview/Common/Logging/ExceptionHook.py
CodeReview/Common/Logging/Logging.py
CodeReview/Common/Logging/__init__.py
CodeReview/Common/Math/Functions.py
CodeReview/Common/Math/Interval.py
CodeReview/Common/Math/__init__.py
CodeReview/Config/Config.py
CodeReview/Config/ConfigInstall.py
CodeReview/Config/Messages.py
CodeReview/Config/__init__.py
CodeReview/Config/logging.yml
CodeReview/Diff/RawTextDocument.py
CodeReview/Diff/RawTextDocumentDiff.py
CodeReview/Diff/SyntaxHighlighter.py
CodeReview/Diff/TextDocumentDiffModel.py
CodeReview/Diff/TextDocumentModel.py
CodeReview/Diff/__init__.py
CodeReview/GUI/__init__.py
CodeReview/GUI/Base/GuiApplicationBase.py
CodeReview/GUI/Base/MainWindowBase.py
CodeReview/GUI/Base/__init__.py
CodeReview/GUI/DiffViewer/DiffViewerApplication.py
CodeReview/GUI/DiffViewer/DiffViewerMainWindow.py
CodeReview/GUI/DiffViewer/DiffWidget.py
CodeReview/GUI/DiffViewer/DiffWidgetConfig.py
CodeReview/GUI/DiffViewer/LexerCache.py
CodeReview/GUI/DiffViewer/SyntaxHighlighterStyle.py
CodeReview/GUI/DiffViewer/__init__.py
CodeReview/GUI/Forms/CriticalErrorForm.py
CodeReview/GUI/Forms/__init__.py
CodeReview/GUI/LogBrowser/CommitTableModel.py
CodeReview/GUI/LogBrowser/LogBrowserApplication.py
