Metadata-Version: 2.1
Name: CodeReview
Version: 1.1.0
Summary: CodeReview is a Python 3 / Qt5 GUI to perform code review on files and Git repositories.
Home-page: https://github.com/FabriceSalvaire/CodeReview
Author: Fabrice Salvaire
Author-email: fabrice.salvaire@orange.fr
Maintainer: Fabrice Salvaire
Maintainer-email: fabrice.salvaire@orange.fr
License: GPLv3
Project-URL: Documentation, https://github.com/FabriceSalvaire/CodeReview
Project-URL: Code, https://github.com/FabriceSalvaire/CodeReview
Project-URL: Issue Tracker, https://github.com/FabriceSalvaire/CodeReview/issues
Keywords: code review diff viewer git
Platform: any
Classifier: Topic :: Software Development :: Version Control
Classifier: Intended Audience :: Developers
Classifier: Development Status :: 5 - Production/Stable
Classifier: License :: OSI Approved :: GNU General Public License (GPL)
Classifier: Operating System :: OS Independent
Classifier: Programming Language :: Python :: 3.8
Requires-Python: >=3.8
